kucoincli/__init__.py
kucoincli/client.py
kucoincli/pipe.py
kucoincli/sockets/__init__.py
kucoincli/sockets/manager.py
kucoincli/sockets/subscribe.py
kucoincli/utils/__init__.py
kucoincli/utils/_helpers.py
kucoincli/utils/_kucoinexceptions.py
kucoin_cli-1.1.1.dist-info/LICENSE
kucoin_cli-1.1.1.dist-info/METADATA
kucoin_cli-1.1.1.dist-info/WHEEL
kucoin_cli-1.1.1.dist-info/top_level.txt
kucoin_cli-1.1.1.dist-info/RECORD
